satcomum/__init__.py
satcomum/br.py
satcomum/constantes.py
satcomum/ersat.py
satcomum/util.py
satcomum-2.2.dist-info/LICENSE
satcomum-2.2.dist-info/METADATA
satcomum-2.2.dist-info/WHEEL
satcomum-2.2.dist-info/top_level.txt
satcomum-2.2.dist-info/RECORD
